LICENSE
MANIFEST.in
README.md
setup.py
asteriskonf/__init__.py
asteriskonf/cli.py
asteriskonf/parser.py
asteriskonf.egg-info/PKG-INFO
asteriskonf.egg-info/SOURCES.txt
asteriskonf.egg-info/dependency_links.txt
asteriskonf.egg-info/entry_points.txt
asteriskonf.egg-info/top_level.txt
asteriskonf.egg-info/zip-safe