Metadata-Version: 1.1
Name: asteriskonf
Version: 0.2
Summary: Export Asterisk configuration file
Home-page: https://github.com/osantana/asteriskonf
Author: Osvaldo Santana Neto
Author-email: asteriskonf@osantana.me
License: The MIT License (MIT)
